motoman/__init__.py
motoman/commands/__init__.py
motoman/commands/devices/__init__.py
motoman/commands/devices/ports.py
motoman/commands/some_commands.py
motoman/entry.py
motoman/nubia.py
motoman/nubia_context.py
motoman/nubia_plugin.py
motoman/nubia_status.py
motoman-0.1.3.dist-info/entry_points.txt
motoman-0.1.3.dist-info/WHEEL
motoman-0.1.3.dist-info/METADATA
motoman-0.1.3.dist-info/RECORD
