Metadata-Version: 2.1
Name: motoman
Version: 0.1.3
Summary: A command line tool to control a set of stepper motors
Home-page: http://www.technocultureresearch.org
License: GPL3
Keywords: instrumentation,control,motors,serial
Author: Satyam Tiwary
Author-email: satyamtiwary@vvbiotech.com
Requires-Python: >=3.7,<4.0
Classifier: Environment :: MacOS X
Classifier: License :: Other/Proprietary License
Classifier: Programming Language :: Python :: 3
Classifier: Programming Language :: Python :: 3.7
Classifier: Programming Language :: Python :: 3.8
Classifier: Programming Language :: Python :: 3.9
Classifier: Topic :: Software Development :: Embedded Systems
Classifier: Topic :: System :: Hardware :: Universal Serial Bus (USB)
Requires-Dist: Pygments (>=2.8.1,<3.0.0)
Requires-Dist: prompt-toolkit (>=3.0.17,<4.0.0)
Requires-Dist: pyserial (>=3.5,<4.0)
Requires-Dist: python-nubia (>=0.2b5,<0.3)
Project-URL: Repository, https://github.com/TechnocultureResearch/MotorsManager-CLI
